pm_toolkit/__init__.py
pm_toolkit/data_assert/DataAssert.py
pm_toolkit/exception/GlobalException.py
pm_toolkit/log/Log.py
pm_toolkit/reading_config/ReadingConfig.py
pm_toolkit-1.0.3.dist-info/LICENSE
pm_toolkit-1.0.3.dist-info/METADATA
pm_toolkit-1.0.3.dist-info/WHEEL
pm_toolkit-1.0.3.dist-info/RECORD
