Metadata-Version: 2.1
Name: pm_toolkit
Version: 1.0.3
Summary: 
License: MIT
Author: qingxi
Author-email: 1917320383@qq.com
Requires-Python: >=3.9,<4.0
Classifier: License :: OSI Approved :: MIT License
Classifier: Programming Language :: Python :: 3
Classifier: Programming Language :: Python :: 3.9
Classifier: Programming Language :: Python :: 3.10
Classifier: Programming Language :: Python :: 3.11
Classifier: Programming Language :: Python :: 3.12
Requires-Dist: build (>=1.2.1,<2.0.0)
Requires-Dist: pyyaml (==6.0.1)
Requires-Dist: uuid (>=1.30,<2.0)
Requires-Dist: xmltodict (>=0.13.0,<0.14.0)
